CHANGES.rst
MANIFEST.in
README.rst
requirements.txt
setup.py
hybrid_crypto/__init__.py
hybrid_crypto/aes.py
hybrid_crypto/crypto.py
hybrid_crypto/utils.py
hybrid_crypto.egg-info/PKG-INFO
hybrid_crypto.egg-info/SOURCES.txt
hybrid_crypto.egg-info/dependency_links.txt
hybrid_crypto.egg-info/requires.txt
hybrid_crypto.egg-info/top_level.txt