Metadata-Version: 1.1
Name: hybrid-crypto
Version: 0.1.0-dev
Summary: Python module which exposes a simple hybrid cryptography abstraction on top of KeyCzar and pycrypto.
Home-page: https://github.com/Kami/python-hybrid-crypto/
Author: Tomaz Muraus
Author-email: tomaz+pypi@tomaz.me
License: Apache License (2.0)
Platform: UNKNOWN
Classifier: Development Status :: 2 - Pre-Alpha
Classifier: Environment :: Console
Classifier: Intended Audience :: Developers
Classifier: Intended Audience :: System Administrators
Classifier: Operating System :: OS Independent
Classifier: License :: OSI Approved :: Apache Software License
Classifier: Programming Language :: Python
Classifier: Programming Language :: Python :: 2.6
Classifier: Programming Language :: Python :: 2.7
Classifier: Programming Language :: Python :: Implementation :: PyPy
Classifier: Topic :: Software Development :: Libraries :: Python Modules
